zdd_algorithms/__init__.py
zdd_algorithms/zdd.py
zdd_algorithms-0.1.4.dist-info/LICENSE
zdd_algorithms-0.1.4.dist-info/METADATA
zdd_algorithms-0.1.4.dist-info/WHEEL
zdd_algorithms-0.1.4.dist-info/top_level.txt
zdd_algorithms-0.1.4.dist-info/RECORD
