Metadata-Version: 2.1
Name: zdd-algorithms
Version: 0.1.4
Summary: Implements the zdd algorithms that are on the wiki page
Home-page: https://github.com/Thilo-J/zdd_algorithms
Author: Thilo Langensteiner
Author-email: <thilo.j.la@gmail.com>
License: UNKNOWN
Project-URL: GitHub, https://github.com/Thilo-J/zdd_algorithms
Keywords: python,zdd,bdd,zsdd,zero-suppressed,decision diagram
Platform: UNKNOWN
Classifier: Development Status :: 4 - Beta
Classifier: Intended Audience :: Education
Classifier: Programming Language :: Python :: 3
Classifier: Operating System :: Unix
Classifier: Operating System :: MacOS :: MacOS X
Classifier: Operating System :: Microsoft :: Windows
Requires-Dist: graphviz
